easynmt/EasyNMT.py
easynmt/__init__.py
easynmt/util.py
easynmt/models/AutoModel.py
easynmt/models/OpusMT.py
easynmt/models/__init__.py
optimumEasyNMT-2.0.8.dist-info/LICENSE
optimumEasyNMT-2.0.8.dist-info/METADATA
optimumEasyNMT-2.0.8.dist-info/NOTICE.txt
optimumEasyNMT-2.0.8.dist-info/WHEEL
optimumEasyNMT-2.0.8.dist-info/top_level.txt
optimumEasyNMT-2.0.8.dist-info/RECORD
