Metadata-Version: 2.1
Name: optimumEasyNMT
Version: 2.0.8
Summary: Easy to use state-of-the-art Neural Machine Translation
Home-page: https://github.com/UKPLab/EasyNMT
Author: Nils Reimers
Author-email: info@nils-reimers.de
License: Apache License 2.0
Download-URL: https://github.com/UKPLab/EasyNMT/archive/v2.0.2.zip
Keywords: Neural Machine Translation
Platform: UNKNOWN
Classifier: Development Status :: 4 - Beta
Classifier: Intended Audience :: Science/Research
Classifier: License :: OSI Approved :: Apache Software License
Classifier: Programming Language :: Python :: 3.7
Classifier: Topic :: Scientific/Engineering :: Artificial Intelligence
Requires-Dist: tqdm
Requires-Dist: transformers (<5,>=4.4)
Requires-Dist: torch (>=1.6.0)
Requires-Dist: numpy
Requires-Dist: nltk
Requires-Dist: lingua-language-detector
Requires-Dist: sentencepiece
Requires-Dist: optimum[onnxruntime-gpu] (<2,>=1.5)
Requires-Dist: aiohttp (<5,>=3.8.1)
